code2json/__init__.py
code2json/code2json.py
code2json/cmd/__init__.py
code2json/cmd/cmd.py
code2json-0.1.0.dist-info/LICENSE
code2json-0.1.0.dist-info/METADATA
code2json-0.1.0.dist-info/WHEEL
code2json-0.1.0.dist-info/entry_points.txt
code2json-0.1.0.dist-info/top_level.txt
code2json-0.1.0.dist-info/RECORD
