Metadata-Version: 2.1
Name: code2json
Version: 0.1.0
Summary: A tool to easily automatically write all your source code to a JSON file and the other way around
Home-page: https://gitlab.com/Deathray_II/code2json
Author: Jasper Steegmans
Author-email: jasper.steegmans.code@gmail.com
License: Apache-2.0
Platform: UNKNOWN
Classifier: Programming Language :: Python :: 3
Classifier: License :: OSI Approved :: Apache Software License
Classifier: Operating System :: OS Independent
Requires-Python: >=3
